odoo/addons/gamification_badge_report/README.rst
odoo/addons/gamification_badge_report/__init__.py
odoo/addons/gamification_badge_report/__manifest__.py
odoo/addons/gamification_badge_report/i18n/es.po
odoo/addons/gamification_badge_report/i18n/gamification_badge_report.pot
odoo/addons/gamification_badge_report/i18n/it.po
odoo/addons/gamification_badge_report/readme/CONTRIBUTORS.rst
odoo/addons/gamification_badge_report/readme/CREDITS.rst
odoo/addons/gamification_badge_report/readme/DESCRIPTION.rst
odoo/addons/gamification_badge_report/report/__init__.py
odoo/addons/gamification_badge_report/report/gamification_badge_report.py
odoo/addons/gamification_badge_report/report/gamification_badge_report_view.xml
odoo/addons/gamification_badge_report/security/ir.model.access.csv
odoo/addons/gamification_badge_report/static/description/icon.png
odoo/addons/gamification_badge_report/static/description/index.html
odoo13_addon_gamification_badge_report-13.0.1.0.1.dev7.dist-info/METADATA
odoo13_addon_gamification_badge_report-13.0.1.0.1.dev7.dist-info/WHEEL
odoo13_addon_gamification_badge_report-13.0.1.0.1.dev7.dist-info/top_level.txt
odoo13_addon_gamification_badge_report-13.0.1.0.1.dev7.dist-info/RECORD
